spacy_transformers/__init__.py
spacy_transformers/align.cp313-win_amd64.pyd
spacy_transformers/align.cpp
spacy_transformers/align.pyi
spacy_transformers/align.pyx
spacy_transformers/annotation_setters.py
spacy_transformers/architectures.py
spacy_transformers/data_classes.py
spacy_transformers/pipeline_component.py
spacy_transformers/py.typed
spacy_transformers/span_getters.py
spacy_transformers/truncate.py
spacy_transformers/util.py
spacy_transformers/layers/__init__.py
spacy_transformers/layers/_util.py
spacy_transformers/layers/hf_shim.py
spacy_transformers/layers/hf_wrapper.py
spacy_transformers/layers/listener.py
spacy_transformers/layers/split_trf.py
spacy_transformers/layers/transformer_model.py
spacy_transformers/layers/trfs2arrays.py
spacy_transformers/tests/__init__.py
spacy_transformers/tests/enable_gpu.py
spacy_transformers/tests/test_alignment.py
spacy_transformers/tests/test_configs.py
spacy_transformers/tests/test_data_classes.py
spacy_transformers/tests/test_deprecations.py
spacy_transformers/tests/test_model_sequence_classification.py
spacy_transformers/tests/test_model_wrapper.py
spacy_transformers/tests/test_pipeline_component.py
spacy_transformers/tests/test_serialize.py
spacy_transformers/tests/test_spanners.py
spacy_transformers/tests/test_textcatcnn.py
spacy_transformers/tests/test_tok2vectransformer.py
spacy_transformers/tests/test_truncation.py
spacy_transformers/tests/util.py
spacy_transformers/tests/regression/__init__.py
spacy_transformers/tests/regression/test_spacy_issue6401.py
spacy_transformers/tests/regression/test_spacy_issue7029.py
spacy_transformers_specifind-1.3.10.dist-info/licenses/LICENSE
spacy_transformers_specifind-1.3.10.dist-info/METADATA
spacy_transformers_specifind-1.3.10.dist-info/WHEEL
spacy_transformers_specifind-1.3.10.dist-info/entry_points.txt
spacy_transformers_specifind-1.3.10.dist-info/top_level.txt
spacy_transformers_specifind-1.3.10.dist-info/RECORD
