Metadata-Version: 2.4
Name: spacy-transformers-specifind
Version: 1.3.10
Summary: spaCy pipelines for pre-trained BERT and other transformers bumped version for Specifind
Home-page: https://spacy.io
Author: Explosion
Author-email: contact@explosion.ai
License: MIT
Classifier: Development Status :: 5 - Production/Stable
Classifier: Environment :: Console
Classifier: Intended Audience :: Developers
Classifier: Intended Audience :: Science/Research
Classifier: Topic :: Scientific/Engineering
Classifier: Topic :: Scientific/Engineering :: Artificial Intelligence
Classifier: License :: OSI Approved :: MIT License
Classifier: Operating System :: POSIX :: Linux
Classifier: Operating System :: MacOS :: MacOS X
Classifier: Operating System :: Microsoft :: Windows
Classifier: Programming Language :: Python :: 3
Classifier: Programming Language :: Python :: 3.7
Classifier: Programming Language :: Python :: 3.8
Classifier: Programming Language :: Python :: 3.9
Classifier: Programming Language :: Python :: 3.10
Classifier: Programming Language :: Python :: 3.11
Requires-Python: <3.14,>=3.9
License-File: LICENSE
Requires-Dist: spacy<4.1.0,>=3.5.0
Requires-Dist: numpy>=1.15.0; python_version < "3.9"
Requires-Dist: numpy>=1.19.0; python_version >= "3.9"
Requires-Dist: transformers<=4.56.1,>=3.4.0
Requires-Dist: torch>=1.8.0
Requires-Dist: srsly<3.0.0,>=2.4.0
Requires-Dist: dataclasses<1.0,>=0.6; python_version < "3.7"
Requires-Dist: spacy-alignments<1.0.0,>=0.7.2
Provides-Extra: cuda
Requires-Dist: cupy>=5.0.0b4; extra == "cuda"
Provides-Extra: cuda80
Requires-Dist: cupy-cuda80>=5.0.0b4; extra == "cuda80"
Provides-Extra: cuda90
Requires-Dist: cupy-cuda90>=5.0.0b4; extra == "cuda90"
Provides-Extra: cuda91
Requires-Dist: cupy-cuda91>=5.0.0b4; extra == "cuda91"
Provides-Extra: cuda92
Requires-Dist: cupy-cuda92>=5.0.0b4; extra == "cuda92"
Provides-Extra: cuda100
Requires-Dist: cupy-cuda100>=5.0.0b4; extra == "cuda100"
Provides-Extra: cuda101
Requires-Dist: cupy-cuda101>=5.0.0b4; extra == "cuda101"
Provides-Extra: cuda102
Requires-Dist: cupy-cuda102>=5.0.0b4; extra == "cuda102"
Provides-Extra: cuda110
Requires-Dist: cupy-cuda110>=5.0.0b4; extra == "cuda110"
Provides-Extra: cuda111
Requires-Dist: cupy-cuda111>=5.0.0b4; extra == "cuda111"
Provides-Extra: cuda112
Requires-Dist: cupy-cuda112>=5.0.0b4; extra == "cuda112"
Dynamic: license-file
